halohomeapi/__init__.py
halohomeapi-0.7.0.dist-info/LICENSE
halohomeapi-0.7.0.dist-info/METADATA
halohomeapi-0.7.0.dist-info/WHEEL
halohomeapi-0.7.0.dist-info/top_level.txt
halohomeapi-0.7.0.dist-info/RECORD
