Metadata-Version: 2.1
Name: halohomeapi
Version: 0.7.0
Summary: A python library to control Eaton HALO Home Smart Lights
Home-page: https://github.com/deadman96385/halohomeapi
Author: Naya Verdier
License: MIT
Platform: UNKNOWN
Classifier: Programming Language :: Python
Classifier: Programming Language :: Python :: 3
Requires-Python: >=3.7
License-File: LICENSE
Requires-Dist: aiohttp (~=3.7)
Requires-Dist: bleak (~=0.13)
Requires-Dist: csrmesh (~=0.10)
Provides-Extra: dev
Requires-Dist: black (==21.9b0) ; extra == 'dev'
Requires-Dist: flake8 (==4.0.1) ; extra == 'dev'
Requires-Dist: flake8-bugbear (==21.9.2) ; extra == 'dev'
Requires-Dist: isort (==5.9.3) ; extra == 'dev'
Requires-Dist: twine (==3.4.2) ; extra == 'dev'
Requires-Dist: wheel (==0.37.0) ; extra == 'dev'
